{
    "gitignore.nix": {
        "branch": "master",
        "description": "Nix functions for filtering local git sources",
        "homepage": "",
        "owner": "hercules-ci",
        "repo": "gitignore.nix",
        "rev": "637db329424fd7e46cf4185293b9cc8c88c95394",
        "sha256": "02wxkdpbhlm3yk5mhkhsp3kwakc16xpmsf2baw57nz1dg459qv8w",
        "type": "tarball",
        "url": "https://github.com/hercules-ci/gitignore.nix/archive/637db329424fd7e46cf4185293b9cc8c88c95394.tar.gz",
        "url_template": "https://github.com/<owner>/<repo>/archive/<rev>.tar.gz"
    },
    "niv": {
        "branch": "master",
        "description": "Easy dependency management for Nix projects",
        "homepage": "https://github.com/nmattia/niv",
        "owner": "nmattia",
        "repo": "niv",
        "rev": "d67c25f29716fd2087e71352783fcce194303a9a",
        "sha256": "1813r42sz4pmv1syn38s281lmg2l7h779q4r33nn5azm7wy45yrh",
        "type": "tarball",
        "url": "https://github.com/nmattia/niv/archive/d67c25f29716fd2087e71352783fcce194303a9a.tar.gz",
        "url_template": "https://github.com/<owner>/<repo>/archive/<rev>.tar.gz"
    },
    "nixpkgs": {
        "branch": "nixpkgs-unstable",
        "description": "Nix Packages collection",
        "homepage": "",
        "owner": "NixOS",
        "repo": "nixpkgs",
        "rev": "fa9a51752f1b5de583ad5213eb621be071806663",
        "sha256": "1i3zj5lj8cg7av8q26dwamchxaxg8a7f2pfaxzdcgy89f839zyjl",
        "type": "tarball",
        "url": "https://github.com/NixOS/nixpkgs/archive/fa9a51752f1b5de583ad5213eb621be071806663.tar.gz",
        "url_template": "https://github.com/<owner>/<repo>/archive/<rev>.tar.gz"
    }
}
